README.md
setup.py
bin/__init__.py
bin/augmenter.py
bin/rerank.py
lib/__init__.py
lib/levenshtein.py
lib/kenlm_python/__init__.py
lib/kenlm_python/example.py
nbestreranker.egg-info/PKG-INFO
nbestreranker.egg-info/SOURCES.txt
nbestreranker.egg-info/dependency_links.txt
nbestreranker.egg-info/entry_points.txt
nbestreranker.egg-info/requires.txt
nbestreranker.egg-info/top_level.txt